djangofloor/__init__.py
djangofloor/admin.py
djangofloor/backends.py
djangofloor/celery.py
djangofloor/checks.py
djangofloor/context_processors.py
djangofloor/deb_fixes.py
djangofloor/decorators.py
djangofloor/df_redis.py
djangofloor/df_ws4redis.py
djangofloor/empty.py
djangofloor/exceptions.py
djangofloor/forms.py
djangofloor/functions.py
djangofloor/iniconf.py
djangofloor/log.py
djangofloor/middleware.py
djangofloor/models.py
djangofloor/root_urls.py
djangofloor/scripts.py
djangofloor/tasks.py
djangofloor/urls.py
djangofloor/utils.py
djangofloor/conf/__init__.py
djangofloor/conf/auth.py
djangofloor/conf/callables.py
djangofloor/conf/config_values.py
djangofloor/conf/defaults.py
djangofloor/conf/fields.py
djangofloor/conf/mapping.py
djangofloor/conf/merger.py
djangofloor/conf/pipeline.py
djangofloor/conf/providers.py
djangofloor/conf/settings.py
djangofloor/conf/social_providers.py
djangofloor/locale/fr_FR/LC_MESSAGES/django.mo
djangofloor/locale/fr_FR/LC_MESSAGES/django.po
djangofloor/management/__init__.py
djangofloor/management/base.py
djangofloor/management/dockerize.py
djangofloor/management/commands/__init__.py
djangofloor/management/commands/celery.py
djangofloor/management/commands/collectstatic.py
djangofloor/management/commands/config.py
djangofloor/management/commands/config_example.py
djangofloor/management/commands/dumpdb.py
djangofloor/management/commands/gen_dev_files.py
djangofloor/management/commands/npm.py
djangofloor/management/commands/packaging.py
djangofloor/management/commands/server.py
djangofloor/management/commands/social_authentications.py
djangofloor/management/commands/worker.py
djangofloor/migrations/0001_initial.py
djangofloor/migrations/0002_notification_notificationread.py
djangofloor/migrations/0003_auto_20180822_0654.py
djangofloor/migrations/__init__.py
djangofloor/signals/__init__.py
djangofloor/signals/bootstrap3.py
djangofloor/signals/html.py
djangofloor/static/admin/img/icon-info.svg
djangofloor/static/bootstrap3/DEPRECATED
djangofloor-1.2.11.dist-info/LICENSE
djangofloor-1.2.11.dist-info/METADATA
djangofloor-1.2.11.dist-info/WHEEL
djangofloor-1.2.11.dist-info/entry_points.txt
djangofloor-1.2.11.dist-info/top_level.txt
djangofloor-1.2.11.dist-info/RECORD
